shoop_checkoutfi/__init__.py
shoop_checkoutfi/apps.py
shoop_checkoutfi/checkoutfi.py
shoop_checkoutfi/payment_method.py
shoop_checkoutfi-0.1.dist-info/DESCRIPTION.rst
shoop_checkoutfi-0.1.dist-info/METADATA
shoop_checkoutfi-0.1.dist-info/RECORD
shoop_checkoutfi-0.1.dist-info/WHEEL
shoop_checkoutfi-0.1.dist-info/entry_points.txt
shoop_checkoutfi-0.1.dist-info/metadata.json
shoop_checkoutfi-0.1.dist-info/top_level.txt
