Metadata-Version: 2.0
Name: shoop-checkoutfi
Version: 0.1
Summary: Shoop Checkout.fi Integration
Home-page: UNKNOWN
Author: UNKNOWN
Author-email: UNKNOWN
License: UNKNOWN
Platform: UNKNOWN
